LICENSE
MANIFEST.in
README.rst
setup.cfg
setup.py
directory_tree/__init__.py
directory_tree/admin.py
directory_tree/apps.py
directory_tree/models.py
directory_tree/tests.py
directory_tree/urls.py
directory_tree/views.py
directory_tree/__pycache__/__init__.cpython-37.pyc
directory_tree/__pycache__/admin.cpython-37.pyc
directory_tree/__pycache__/models.cpython-37.pyc
directory_tree/__pycache__/urls.cpython-37.pyc
directory_tree/__pycache__/views.cpython-37.pyc
directory_tree/migrations/__init__.py
directory_tree/migrations/__pycache__/__init__.cpython-37.pyc
directory_tree/templates/directory_tree_base.html
directory_tree/templates/directory_tree/directory_tree_index.html
directory_tree/templates/directory_tree/static/js/app.js
directory_tree/templates/directory_tree/static/js/main.js
directory_tree/templates/directory_tree/static/js/templates.js
directory_tree/utils/decorators.py
directory_tree/utils/directory_tree.py
directory_tree/utils/get_list_folder.py
directory_tree/utils/settings_models.py
directory_tree/utils/__pycache__/decorators.cpython-37.pyc
directory_tree/utils/__pycache__/directory_tree.cpython-37.pyc
directory_tree/utils/__pycache__/get_list_folder.cpython-37.pyc
directory_tree/utils/__pycache__/settings_models.cpython-37.pyc
django_directory_tree.egg-info/PKG-INFO
django_directory_tree.egg-info/SOURCES.txt
django_directory_tree.egg-info/dependency_links.txt
django_directory_tree.egg-info/requires.txt
django_directory_tree.egg-info/top_level.txt